{
    "id": "53",
    "name": "Atmospheric Writing Music",
    "number": "2054274628",
    "snakeCode": "EI",
    "numberUnderlined": false,
    "picture": {
        "hat": "16",
        "eye": "1",
        "human": "0",
        "mouth": "_"
    },
    "gridCode": [
        [
            false,
            false,
            false,
            true
        ],
        [
            false,
            false,
            false,
            false
        ],
        [
            false,
            false,
            false,
            false
        ],
        [
            false,
            false,
            false,
            false
        ]
    ],
    "gridColor": "white"
}