{
    "id": "323",
    "img": {
        "number": "4881520920",
        "snakeCode": "'|.|'| |. '| |. ",
        "underlined": false,
        "idUnderlined": false,
        "picture": {
            "hat": "1",
            "eye": "1",
            "human": "1",
            "mouth": "."
        },
        "grid": {
            "code": [
                [
                    "0",
                    "0",
                    "1",
                    "0"
                ],
                [
                    "0",
                    "0",
                    "0",
                    "0"
                ],
                [
                    "0",
                    "0",
                    "0",
                    "0"
                ],
                [
                    "0",
                    "0",
                    "0",
                    "0"
                ]
            ],
            "color": "#0000fe"
        },
        "colors": [
            "#5135ea",
            "#9d4b35",
            "#c2ebb3",
            "#19759e",
            "#ea9e7c",
            "#eb9735",
            "#35cfeb"
        ],
        "backgroundColor": "#00ff43"
    },
    "name": "Calm Cyberpunk Music"
}