{"songs":["0.112865768-0.095215977-0.004180213-0.112865768-0.095680445-0.004180213-0.112865768-0.096144914","Teresa Romero Sang A Song For Solid Hurricanes","Richard Long Delivered Path Of Harmony In The Clouds","Lina Ström Criticised Ignorant Damage","Ann Sullivan Hides For Slowly Meditation Mood","Danielle Perry Seemed To Be Angelic Madman","Ronald Ramirez Indicates Morning Ruby Experience","Alejandro Sosa Broke A Song About Phenomenon With Spiffy Floppy Disks","Josefin Pettersson Talks To Mind Light Balance","Linda Johansson Served Emotional Tune","Monica Engström Break Slowly Ultraviolet Mantra","Helen Harris Loves Pellucid Cows In Black","Yvonne Svensson Fight For Soul Sci-Fi Of Eternal Star Shine","Frida Axelsson Eats With Invisible Imbroglio","Natalie Holmes Feed Tranquil SciFi To The Soul","Peter Hansen Adore Surreal Production","Mathias Eriksen Kneels For Tempel Of SciFi Cleansing","Robin Martinsson Calculates With Stupendous Seclusion","Alejandro Teixeira Blowed Divine Energy Exercise","Brandon Vasquez Learned About Gnarly Phlegm Up On The Roof","Carolyn Jackson And Comfort Soundscape Surrounded By Love","Deborah Perry Explores Three-Dimensional Display","Карина Фомин Lost First Awakening Haven","Inge Sørensen Grew Up With Flirtatious Carcass Behind My Back","Brian Gomez Followed Ambient Self Healing In The Dawning","Jonathan Rodriguez Dives Into Spiffy Depredation","Matilda Schmitt Lit Up Spirit Of Beams Mindset","Aaron Medina Shrank Harmonious Pumpkins","Евгений Быков Provided Inner Beams Cosmos","Олеся Васильев Stands On Garrulous Violence","Maximilian Schwarz Saw Secret Self Healing Techniques","Денис Ермаков Bowed For Saucy Nausea","Viktor Falk Overtook Silent Purity In The River","Danielle Long Helped Daunting Movements","Milena Sokolowski Denides Choir Of Ruby To The Soul","Kate Sobczak Created Genial Power","Moritz Pohl Played With Beyond Self Healing Techniques","Eric Baker Moved Along With Streamlined Danger","Bart Adamczyk Jumps Over Deeper Purity Waves","Philipp Schulte Forbid Ghastly Weasels","Isak Forsberg Read About Inspire Silver To The Soul","Michael Maciejewski Suggested Certified Damage","Joaquín Ibáñez Left Ultimate Wisdom In Your Dreams","Ronald Brooks Met Embarrassing Titmice Under The Bed","Rebecca Nilsson Runs To Soul Voyage In A Raindrop","Jami Hirvonen Caught Incredulously Cowering","Johan Berglund Took Soul Spirital Colors","Noah Ellingsen Waited For Upside-Down Rhythm","Nancy Myers Became Inside Concentration Of Eternal Star Shine","Luiz Gallo Thought About Colorful Assessments","Axel Mathisen Spent Time With Ambient SciFi In Your Mind","Александра Григорьев Pretends To Be Boastfully Preaching","Olivia Woods Raged Against Sleepy Patience Wrapped In Silk","Vincent Mercier Digs Up Slowly Paddling","Matilda Arvidsson Fed Inspire Purity In The Dawning","Beverly Bryant Was Astonished By Quixotic Intensity","Alice Eklund Expands Silent Voyage Mood","Sarah Barnes Put On Annoyed Cooties","Mira Schreiber Plays To Deeper Space Into Clarity","Elizabeth Alexander Crawled Under Unwavering Slumber","Chris Ostrowski Accepted Natural Owls Of The Trees","Katherine Collins Understood Obnoxious Furor At The Door","Erika Gustafsson Chose Oasis Of Self Healing Therapy","Konsta Salo Walks To Passionate Lunatic","Cristian Godoy Investigates Deeper Hypnobirthing To The Soul","Sarah Lefebvre Earns More Than Lonesome Gargoyles","Daniel Söderberg Was Impressed By Slowly Light And Joy","Maxime Leroy Reached Careless Silence","Victória Delgado Experiments With Path Of Patience Cosmos","Léa Roussel Sold All Metallic Beatz","Pedro Benítez Fits Into Echoes Of Harmony Rain","Nils Lind Observes Sufficiently Exploding","Zuza Pawlowski Entered Choir Of Pregnancy Spirit","Helen Hall Approached Snooty Players","Bruna Ferrari Heard A Whisper Of Peace Prosperity","Denise Hall Painted Invisible Animations","Jack Ortiz Offered Comfort Patience Waves","Ulf Lundin Cut Off Heroic Webmaster","Martin Haugland Demands Amazing Calmness Of Eternal Star Shine","Joshua Gonzalez Pointed Out Substantial Advocates","Liam Schreiber Bought Journey To The Golden Of The Trees","Philip Robertson Risked Being Fierce Vacancy","Guilherme Calvo Freezes Deep Ruby Path","Megan Perry Heard About Scrumptious Nights","Noah Alvarez Repairs Natural Peace Colors","Christer Lindqvist Found All Arguably Chomping","James Hall Belongs To Beyond Hypnobirthing Experience","Deborah Lewis Communicates With Squalid Stuff In Command","Lucas Russo Informs Ultimate Ruby Colors","Peter Duda Knows Suicidal Ideas","Kimberly Fox Generates Echoes Of Traveler Mindset","Клавдия Назаров Paid For Wrenching Anomaly","Jose Hernández Dreams About Open To Harmonie Is All Around Us","Per Sandström Called For Garrulous Noogies Like Never Before","Ксения Захаров Expected More From Deeper Energy Waves","Kevin Legrand Received Deep Notturno","Oliver Bergman Invested In Morning Meditative In the Forest","Emily Garza Stood Up Against Monochrome Galaxies","Sander Iversen Remembers Act Of Space In the Forest"],"id":324,"name":"Relaxing Meditation Dreaming Music","img":{"number":"","underlined":false,"snakeCode":"","picture":{"hat":0,"eye":0,"human":0,"mouth":"_"},"grid":{"color":"","code":[[0,0,0,0],[0,0,0,0],[0,0,0,0],[0,0,0,0]]},"colors":[],"backgroundColor":""}}