{
    "id": "507",
    "img": {
        "number": "7745649803",
        "snakeCode": " '| |.|' ",
        "underlined": false,
        "idUnderlined": false,
        "picture": {
            "hat": "16",
            "eye": "1",
            "human": "1",
            "mouth": "/"
        },
        "grid": {
            "code": [
                [
                    "0",
                    "0",
                    "0",
                    "0"
                ],
                [
                    "0",
                    "0",
                    "1",
                    "0"
                ],
                [
                    "0",
                    "0",
                    "0",
                    "0"
                ],
                [
                    "0",
                    "0",
                    "0",
                    "0"
                ]
            ],
            "color": "#00ffff"
        },
        "colors": [
            "#a59eeb",
            "#975175",
            "#2736eb",
            "#9d4b35",
            "#75eb7b",
            "#7535eb",
            "#193d9e"
        ],
        "backgroundColor": "#00fffb"
    },
    "name": "Space Soothing Music"
}