{
    "id": "531",
    "img": {
        "number": "6540628433",
        "snakeCode": "'|.|'| |.|' '| |.| '| ",
        "underlined": false,
        "idUnderlined": false,
        "picture": {
            "hat": "1",
            "eye": "1",
            "human": "1",
            "mouth": "_"
        },
        "grid": {
            "code": [
                [
                    "0",
                    "0",
                    "1",
                    "0"
                ],
                [
                    "0",
                    "0",
                    "0",
                    "0"
                ],
                [
                    "0",
                    "0",
                    "0",
                    "0"
                ],
                [
                    "0",
                    "0",
                    "0",
                    "0"
                ]
            ],
            "color": "#00ff01"
        },
        "colors": [
            "#27a566",
            "#9eeb9d",
            "#7bec9e",
            "#4b5175",
            "#5eeb7b",
            "#3deb18",
            "#eb2890"
        ],
        "backgroundColor": "#00edff"
    },
    "name": "Relaxing Ambient Study Music"
}