{"songs":["0.061392563-0.049413526-0.002246069-0.060893436-0.049163963-0.002246069-0.030197154-0.027701522","Donald Johnson Felt Nothing For Nebulized Strain In My Mind","Arthur Parker Protects New Study Better Field","Christine Gutierrez Communicates With Emotionally Shining","Юлия Козлов Crawled Under Mindful Wisdom Is All Around Us","Stig Karlsson Entered Sequestered Knights","Евгения Тарасов Sold All Act Of Pregnancy To The Soul","Carl Gonzales Break Obnoxious Prophets","Luana Barbosa Took Deeper Diamond In Your Memories","Adam Borkowski Stood Up Against Stable Plethora In The Closet","Геннадий Савин Runs To Arriving Owls Child","Patricia Morales Played With Lugubrious Depression","Pablo Correa Explores Peaceful Slumber Shadows","Richard Edwards Grew Up With Analytical Travesties","Klara Hellström Demands Tranquil Ruby In The Dawning","Rachel Ramirez Moved Along With Purple Power","Li Xiu Ying Reached Natural Energy Is All Around Us","Lauren Adams Informs Secluded Pumpkins In A Box","Charles Nichols Fight For Soul Chillout Life","Alan Holmes Expected More From Temporary Frogs","Diana Stephens Found Beyond Awakening Ambience","Nancy James Blowed Sentimental In-Laws","Jose Figueroa Watched Hypnotic Chillout Colors","Laura König Adapted To Digital Conspectus","Klaudia Kowalski Knows Journey To The Dream Mood","Kevin James Became Incredulously Broadcasting","Justin Kim Overtook Flower Of Slumber Ambience","Wojtek Jaworski Sang A Song For Ambitious Hallucinations","Anneli Magnusson Asked About Beyond Meditative Prosperity","Pia Lundqvist Recommends Digitally Fighting","Vincent Alvarez Walks To Internal Harmonie In Your Dreams","Roger Cox Understood Transparent Liquid","Mohammad Hagen Was Astonished By Sea Of Focus Of The Trees","Julia Hahn Found All Joyfully Bashing","Isabella Arnold Was Meant To Be Flower Of Truth Techniques","Александра Савельев Dreams About Ignorant Veins","Beverly Rice Seemed To Be Vital Energy Is All Around Us","Elsa Olsson Spoke To Secluded Labyrinth Under A Tree","Sérgio Rojas Needs Divine Sleep Is All Around Us","Andres Ramos Delivered Flirtatious Gerbils","Andres Correa Included All Deep Awakening Waves","Leon Thorsen Pointed Out Energetic Sheep","Jan Lindqvist Paid For Inside Voyage To The Soul","Sora Sato Jumps Over Prickly Power","Judith Shaw Waited For Balanced Awakening Therapy","Sean Cruz Talks To Flat Vitamins With Toxic Cavatina","Russell Patel And Amazing Background In Your Dreams","Marianne Ekström Put On Daring Nescience","Diana Romano Rang The Bell For Ambient Self Healing Rain","Lauri Hirvonen Lain Next To Lonely Underground","Matteo Winter Broke Ultimate Owls Life","Jacob Lehmann Learned About Bloated Ghosts","Ida Amundsen Kneels For Ambient SciFi Shadows","Felix Bauer Digs Up Supercilious Pain","Максим Демидов Received Spirit Of Sci-Fi Life","Helen Månsson Met Certified Protesters","Jacob Sullivan Lost Journey To The Slumber Life","Igor Cavalcante  Approached Sufficient Brain On The Weekends","Lisa Mills Fed Ambient Soundscape Visualization","Deborah Black Eats With Fatuously Terrorizing","Sara Böhm Raged Against Ambient Concentration Visualization","Agata Ostrowski Indicates Simulated Lunatic","Victoria Foster Freezes Internal Ultraviolet Rain","Alicja Tomaszewski Investigates Kentucky-Fried Egyptians","Alice James Stands On Perfect Space In Your Mind","Amanda Adams Adore Innocently Sneezing","Mark Black Forbid Mindful Sunrise Path","Megan Ruiz Lit Up Nervous Stalkers","Jacqueline West Thought About Divine Soundscape Balance","Kristian Haugland Reduces Garrulous Castles","Кристина Ильин Accepted Mind Emerald Shadows","Valtteri Tuominen Stopped Robust Universe Under The Table","Kirsten Olsen Denides Spirit Of Emerald Therapy","Barbara Jordan Built Quietly Bleeding","Tyler Howard Pretends To Be Sea Of Seeking In Your Memories","Betty Silva Was Impressed By Patiently Swimming","Sora Kato Bought Ultimate Patience Life","Jordan Phillips Believed In Fetid Heaven","Ludvig Olofsson Criticised Divine Voyage In the Forest","Steven Nelson Hides For Saucy Exploration","Mathilde Dumont Read About Balanced Space Path","Jéssica Gomes Expands Mad Travesties","Teresa Kim Discovered Comfort Voyage Field","Mika Franke Experiments With Giddy Pawns","Billy Garcia Invested In Perfect Owls Rain","Harry Jenkins Called For Chaotic Fantasies","Katherine Wells Bowed For Inner Chillout In The Dawning","Hannah Green Added Improvident Imitations","Lucas Gauthier Plays To Morning Awakening Spirit","Stephanie Santos Spent Time With Digitally Paddling","Johanna Lundberg Worked With Mindful Seeking Child","Nicole Jackson Tried Belching Speakers","साई पटेल Saw Arriving Spirital Mantra","Lucas Lehmann Loves Superstitious Tidbits","Sylwia Chmielewski Remembers Balanced Space Experience","Николай Тимофеев Repairs Joyfully Crawling","Judith Nguyen Earns More Than Breathing Self Healing Transformation","Ann Richardson Provided Old-Fashioned Ideas From Hell","Jose Daniels Fits Into Breathing Bloom Wrapped In Silk"],"id":552,"name":"Ambient Meditation Fantasy Music","img":{"number":"","underlined":false,"snakeCode":"","picture":{"hat":0,"eye":0,"human":0,"mouth":"_"},"grid":{"color":"","code":[[0,0,0,0],[0,0,0,0],[0,0,0,0],[0,0,0,0]]},"colors":[],"backgroundColor":""}}