{
    "id": "584",
    "img": {
        "number": "5848358845",
        "snakeCode": "'|.| |.|'| .|'| |.| '|.|' ",
        "underlined": false,
        "idUnderlined": false,
        "picture": {
            "hat": "4",
            "eye": "0",
            "human": "1",
            "mouth": "."
        },
        "grid": {
            "code": [
                [
                    "0",
                    "0",
                    "0",
                    "0"
                ],
                [
                    "0",
                    "0",
                    "0",
                    "0"
                ],
                [
                    "0",
                    "1",
                    "1",
                    "1"
                ],
                [
                    "0",
                    "0",
                    "0",
                    "0"
                ]
            ],
            "color": "#ffffff"
        },
        "colors": [
            "#ec519f",
            "#973566",
            "#3deb27",
            "#1875ec",
            "#3d5174",
            "#2feb97",
            "#7c6d36"
        ],
        "backgroundColor": "#00b8ff"
    },
    "name": "Space Meditation Tranquil Music"
}