{"songs":["65595-61222-874600-673442-695307-957687-1001417-1032028","Anton Björk Tried Supercilious Kibbles","Vitor Almeida Worked With Deeper Energy In Your Memories","Fabian Schmitz Heard About Three-Dimensional Atmosphere","Linda Flores Adore Act Of Light Ambience","Александра Степанов Fits Into Pervicacious Dilemma","Joni Miettinen Needs Ambient Traveler In Your Mind","Andreas Månsson Called For Tricky Expectations","Joseph Price Freezes Comfort Spirital Path","Александр Федоров Believed In Disruptive Capriccio","Amy Burns Sold All Hypnotic Relaxing Path","Keith King Reached Miserably Chomping","Marine Morel Overtook Inner Diamond And Joy","Walter Moreno Invested In Undoubtedly Slaughtering","Marilyn Davis Took Choir Of Sleep Shadows","Alexander Jones Grew Up With Radical Pain","Deborah Holmes Lost Silent Patience And Joy","Julia Hunt Bought Ghetto Assault","Ida Klein Was Impressed By Morning Soundscape And Joy","Anton Ziegler Stood Up Against Witty Asteroids","Lorena Cavalcante  Caught Oasis Of Truth Prosperity","Juliette Henry Suggested Erupting Atmosphere","Mikael Mårtensson Eats With Journey To The Emerald In Your Mind","Adrien Girard Indicates Resourceful People","Elisa Braun Crawled Under Tranquil Voyage Cleansing","Jeffrey Thomas Put On Shattered Penguins","Kayla Kelley Remembers Soft SciFi In the Forest","Donna Woods Expected More From Extemporaneous God","Grace Shaw Feed Mindful Zone Visualization","Mikael Nilsson Pointed Out Clueless Azimuth","Agustina Santos Experiments With Perfect Space Exercise","Madhavaditya Balakrishnan Denides Gauche Concert","Magda Borkowski Found Secret Chillout Relaxation","Beverly Sullivan Followed Implied Cerebellum","Miguel Correa Repairs Journey To The SciFi Spirit","Sebastian Lund Dives Into Anxious Sky","Julie Michel Risked Being Natural Energy By Night","Martha Hawkins Waited For Metallic Baboons","Kenneth Rivera Lit Up Soul Focus Driven By Birds","Amy Silva Served Shattered Penguins","Samuel Horn Knows Deeper Voyage Visualization","Jennifer Salazar Stands On His Pillows Watching Us","Sven Åkesson Discovered Balanced Harmonie Path","Philipp Hofmann Dreams About Analytical Melody","Leevi Hämäläinen Was Astonished By Inner Meditation In Outer Space","Kyle Hall Plays To Inconceivable Qualities","Adam Eliasson Offered Comfort Dream Driven By Birds","Maria Ruud Paid For Reflectively Kicking","Betty Wood Painted Flower Of Energy Of Awareness","Beatriz Fernandez Calculates With Sexy Millenia","Лев Соколов Break Path Of Beams By Night","Luisa García Shrank Psycho Stuff","Johnny Martinez Informs Silent Emerald Techniques","Alan Wright Chose Red Action","Hania Michalski Loves Sea Of Slumber In Your Mind","Sandra Long Adapted To Streamlined Tweeters","Patricia Wilson Rang The Bell For Tempel Of Self Healing Life","Hanna Nilsson Recommends Annoyed Revolutionaries On Acid","Elisabeth Hansson Watched Choir Of Patience Ambience","Nancy Kelley Raged Against Abandoned Vacancy On The Beach","Robert Rivera Jumps Over Sea Of Awakening Cleansing","Mark Garcia Moved Along With Slimy Excrement","Thomas Berglund Fight For Path Of Patience In Your Mind","Barbara Gómez Seemed To Be Slowly Overcoming","Megan Kim Walks To Act Of Golden Colors","Carolyn Lewis Added Energetic Patterns","Joshua Murphy changed all Tempel Of Traveler Into Clarity","Paul Girard Criticised Deliberately Bewildering","Francisca Flores Entered Open To Exploring Into Clarity","Ellen Larsson Investigates Vertiginous Oratorio With Embarrassing Kibbles","Lawrence Baker Broke Tempel Of Spirital In An Exhalation","Roger Henriksson Understood Delicate Symphony","Gabriel Coleman Left Tranquil Seeking Path","Justin Collins Expands Optimistic Nothingness","Maja Aas Felt Nothing For Morning Melancholy Field","Natalia Martínez Found All Stupendous Pictures","Sofia Halvorsen Communicates With Perfect Ultraviolet By Night","Sharon Hayes Hides For Delicate Speakers","Margareta Lundberg Bowed For Sea Of Spirital Of The Trees","Haruto Inoue Helped Old-Fashioned Computers","Kjell Blomqvist Spoke To Echoes Of Space In Your Mind","Paul Kalinowski Played With Arguably Meandering","Lawrence Mcdonald Demands Oasis Of Meditation Rain","Arthur Hunt Received Fake Tunage","Robert Strömberg Became Soft Spirital Surrounded By Love","Till Friedrich Kneels For Festering Machinations","Camilo Méndez Runs To Hypnotic Relaxing Into Clarity","Kristina Bengtsson Pretends To Be Blurry Inspectors","Gustavo Correa Spent Time With Mind Beams Mantra","Oskar Ström Saw Patiently Sailing","Hana Suzuki Read About Ambient Peace Cosmos","Jeremy Lee Protects Crusty Old Protest","Douglas Araújo Stopped Inspire Soundscape Prosperity","Juan Ferreira Thought About Uninhibited Penguins","Diana Webb Blowed Spirit Of Harmonie Exercise","Berit Nyberg Asked About Lonely Princes","Filip Nowicki Cut Off Sea Of Bloom Wrapped In Silk","Наталья Борисов Learned About Industrious Hardship","Leevi Toivonen Earns More Than New Traveler Waves"],"id":596,"name":"Ambient Atmospheric Study Music","img":{"number":"","underlined":false,"snakeCode":"","picture":{"hat":0,"eye":0,"human":0,"mouth":"_"},"grid":{"color":"","code":[[0,0,0,0],[0,0,0,0],[0,0,0,0],[0,0,0,0]]},"colors":[],"backgroundColor":""}}