{"songs":["0.046400611-0.024632423-0.024632423-0.045445865-0.022150085-0.022150085-0.044109222-0.019476799","John Johansson And Jiggling Sisters","Thais Gil Lost Act Of Voyage Spirit","Louis Wallace Talks To Chimerical Thongs","Raymond Medina Calculates With Deep Owls Child","Teemu Kauppinen Was Astonished By Lascivious Princes","Ashley Patel Met Amazing Beams Is All Around Us","Игорь Белов Included All Sexy Artifacts","Zachary Washington Pointed Out Spirit Of Diamond Surrounded By Love","Filip Iversen Became Modest Rage","Elias Solheim Called For Inspire Background Path","Emelie Söderberg Break Tons Of Inspectors","Ann Åkesson Cut Off Arriving Beams Of Eternal Star Shine","David Campbell Communicates With Motionless Banishment","Stephen Cooper Created Deeper Meditation Cosmos","Dennis Lee Observes Colorless Spiders With Mad Demons","Sabrina Morales Digs Up Ambient Dream Path","Russell Martin Repairs Revolutionary Effluvium","Milena Kwiatkowski Grew Up With Inside Harmonie Relaxation","Claes Pettersson Freezes Sensible Rendezvous","Joyce Thomas Indicates Asking For Relaxing In The River","Анатолий Щербаков Sang A Song For Petrified Melody","Dhruv Acharya Kneels For Serenity Truth Balance","Thomas Griffin Reached Optimistic Anomaly","Степан Громов Found Act Of Purity Cosmos","Anna Chavez Painted Defiant Slumber","Beverly Simpson Played With Spirit Of Sci-Fi Cosmos","Nicholas Gardner Chose Spiteful Flatulence Like Never Before","Inka Koskinen Suggested First SciFi Balance","Anthony Davis changed all Sloppy Scandal With Perpendicular Darkness","Alexis Alvarez Generates Act Of Patience Techniques","Stig Falk Plays To Snooty Schadenfreude","Angela Parker Broke Internal Ruby Mood","Benjamin Mendoza Delivered Digitized Assault","Carol Daniels Lit Up Mind Background Waves","Denise Olson Heard Unstable Yuppies","Martha Kelly Found All Perfect Peace Is All Around Us","Brian Simpson Denides Aggressively Lying","Bart Jasiñski Heard About Deep Awakening In Outer Space","Eva Bergman Dreams About Sad Sacks Of Sexuality","Joseph Owens Protects Inner Bloom And Joy","Diana Robertson Understood Unfriendly Vandals","Alan Ford Spent Time With Amazing Truth Into Clarity","Stephen Wallace Discovered Ambitious Mother","Noah Danielsen Caught Serenity Calmness Surrounded By Love","Brittany Reed Feed Vibrating Ineptitude Without Remorse","Maximilian Seidel Believed In Deep Ultraviolet Surrounded By Love","Maya Werner Walks To Genial Gyrations","Jessica Marshall Informs Journey To The Golden In The Dawning","Guilherme Rojas Fits Into Clueless Vacuity","Jérémy Roussel Stopped Secret Sci-Fi In An Exhalation","Daniel Mcdonald Watched Cyber- Asteroids","Lotta Braun Invested In Morning Light Haven","Juan Chen Waited For Possessive Players Under Fire","Angela Garza Reduces Soft Space Driven By Birds","Илья Степанов Sold All Happily Tweaking","Stefan Olofsson Raged Against Amazing Study Better In An Exhalation","Siv Fredriksson Took Stupid Obstacles","Juan Rodríguez Accepted Balanced Chillout Therapy","Laura Schubert Fed Fast Troglodyte","Venla Lahtinen Remembers Echoes Of Study Better Experience","Paul Edwards Explores Playful Associations","Sami Nurmi Moved Along With Ultimate Melancholy Of Awareness","Zachary Crawford Bowed For Deadly Burial","Jeffrey Carter Adapted To New Light In Your Memories","Julia Ferrari Offered Arrogant Romantic In My Pants","Elias Winter Thought About Act Of Exploring Surrounded By Love","Ella Walter Needs Lonesome Dinosaurs With Romantic Piranha","Gloria Washington Loves Tempel Of Light Haven","Tim Heinrich Eats With Froody Whispers","Sander Halvorsen Stands On Divine Seeking Therapy","Annika Wallin Paid For Daunting Blossom","Liam Walter Risked Being Mind Hypnobirthing Mantra","Roger Black Recommends Cool Inspectors In The Mirror","Юрий Белов Earns More Than Vital Meditation In The Dawning","Emelie Ali Left Dirty Father Far From Home","Jakub Kowalski Woke Up Next To Flower Of Soundscape In An Exhalation","Adrien Clement Seemed To Be Superficial Horrors","Michał Kamiñski Rang The Bell For Comfort Miracle Rain","空 井上 Belongs To Obstreperous Pariah","Frida Fredriksson Built Open To Golden Shadows","Mona Nyström Was Impressed By Fertile Cowboys","Margaret Stevens Entered Oasis Of Melancholy In The River","Elisa Schreiber Blowed Chocolate-Covered Protest","Claes Jansson Worked With Divine Sunrise To The Soul","Cheryl Gordon Saw Illogical Statues","Cynthia Tran Added Sea Of Slumber Mindset","Jéssica Cavalcante  Stood Up Against Resourceful Hemorrhoids","Олеся Новиков Followed Soft Chillout Cleansing","Joe Lee Shrank Swiftly Flying","Kathryn Taylor Criticised Comfort Study Better Colors","Susan Hernandez Forbid Pervicacious Specifications","Vinicius Sosa Asked About Comfort Diamond In The Dawning","Pia Pedersen Investigates Diligent Molecules On The Battlefield","Camila Herrera Helped Tranquil Voyage By Night","Лев Федоров Dives Into Quiet Blossom","Elisa Martin Expands Deep Zone Life","Alan Nelson Fight For Uninvited Party","Mikolaj Król Kucharski Provided Oasis Of Chillout Is All Around Us"],"id":696,"name":"Cosmic Inspiring Music","img":{"number":"","underlined":false,"snakeCode":"","picture":{"hat":0,"eye":0,"human":0,"mouth":"_"},"grid":{"color":"","code":[[0,0,0,0],[0,0,0,0],[0,0,0,0],[0,0,0,0]]},"colors":[],"backgroundColor":""}}