{
    "id": "757",
    "img": {
        "number": "A",
        "snakeCode": " '|.|' |. '| |. '| | ",
        "underlined": false,
        "idUnderlined": false,
        "picture": {
            "hat": "2",
            "eye": "0",
            "human": "0",
            "mouth": "_"
        },
        "grid": {
            "code": [
                [
                    "0",
                    "0",
                    "0",
                    "0"
                ],
                [
                    "0",
                    "0",
                    "1",
                    "0"
                ],
                [
                    "0",
                    "0",
                    "0",
                    "0"
                ],
                [
                    "0",
                    "0",
                    "0",
                    "0"
                ]
            ],
            "color": "#00ffff"
        },
        "colors": [
            "#7a9eea",
            "#7b7567",
            "#c1ea82",
            "#195174",
            "#3da568",
            "#cfeb1a",
            "#3d9e35"
        ],
        "backgroundColor": "#010bff"
    },
    "name": "Ambience Realxing Background Music"
}