{
    "id": "790",
    "img": {
        "number": "2408514006",
        "snakeCode": "'| |.|'| '|.| |.| '|.|' ",
        "underlined": false,
        "idUnderlined": false,
        "picture": {
            "hat": "2",
            "eye": "0",
            "human": "0",
            "mouth": "."
        },
        "grid": {
            "code": [
                [
                    "0",
                    "0",
                    "0",
                    "0"
                ],
                [
                    "0",
                    "0",
                    "0",
                    "0"
                ],
                [
                    "0",
                    "1",
                    "1",
                    "1"
                ],
                [
                    "0",
                    "0",
                    "0",
                    "0"
                ]
            ],
            "color": "#fe0000"
        },
        "colors": [
            "#369098",
            "#9e1976",
            "#2f5176",
            "#43eb50",
            "#9ed0eb",
            "#59a598",
            "#9eeb21"
        ],
        "backgroundColor": "#1500ff"
    },
    "name": "Background Cosmic Music"
}