{
    "id": "791",
    "img": {
        "number": "A",
        "snakeCode": "'|.|'|. |.|' ' | ",
        "underlined": false,
        "idUnderlined": false,
        "picture": {
            "hat": "1",
            "eye": "0",
            "human": "0",
            "mouth": "/"
        },
        "grid": {
            "code": [
                [
                    "0",
                    "0",
                    "0",
                    "1"
                ],
                [
                    "0",
                    "0",
                    "0",
                    "0"
                ],
                [
                    "0",
                    "0",
                    "0",
                    "0"
                ],
                [
                    "0",
                    "0",
                    "0",
                    "0"
                ]
            ],
            "color": "#fe0000"
        },
        "colors": [
            "#c1eb9f",
            "#1a675f",
            "#517643",
            "#ea9e7c",
            "#ec8236",
            "#7c8268",
            "#35eab3"
        ],
        "backgroundColor": "#1700ff"
    },
    "name": "Relaxing Meditation Background Music"
}