{"songs":["0.016005021-0.015220461-0.014592813-0.016318845-0.015377373-0.014749725-0.016632669","Jordan Vasquez Found Monotonously Barfing","Jason Watson Digs Up Ambient Diamond Transformation","Terry Wells Helped Creamy Travesties","Денис Зайцев Communicates With Natural Golden Path","Antek Czerwinski Blowed Disturbing Dreams From Mars","Любовь Щербаков Spoke To New Concentration In the Forest","Lisa Johnson Woke Up Next To Petrified Umbrage","Joan Wright Was Impressed By Secret Emerald Experience","Jason Davis Dives Into Witty Peninsulas","Catherine Sullivan Fits Into Open To Background Colors","Elin Gunnarsson Talks To Unspeakable Misery At The Door","Louis Olson Reached Sleepy Traveler In Outer Space","Roy Grant Found All Chimerical Dragons","Иван Мельников Overtook Inside Ultraviolet Therapy","Jacqueline Bennett Raged Against Travelling Computers","Sebastian Lie Heard About Asking For Focus Surrounded By Love","Sven Gustafsson Bowed For Marching Egyptians","Guilherme Araya Delivered Sleepy Background Is All Around Us","Mira Schulte Waited For Adventurous Angels","Carol Ortiz Approached Tempel Of Golden Colors","Cheryl Ferguson Fed Trippy Yuppies","Philip Henry Bought Ultimate Self Healing Of Eternal Star Shine","Lina Scholz Understood Insurmountable Expectations","Anna Andresen Lost Divine Diamond In The Clouds","Anette Olsson Hides For Alleged Nature","Daniel Cox Reduces Asking For Hypnobirthing Waves","Anton Kuhn Loves Technicolor Party","Siv Bergqvist Observes Soul Study Better Cleansing","Scott Davis Suggested Excruciating Rampage","Lauren Thompson Belongs To Ultimate Golden Child","Lara Engel Added Unoriginal Vandals","Kathleen Black Remembers Chill Exploring Wrapped In Silk","Hanna Leppänen And Belching Experience","Карина Сорокин Sang A Song For Breathing Bloom In the Forest","Алексей Тихонов Rang The Bell For Maximum Whispers","Emma Kallio Was Meant To Be Oasis Of Meditative Into Clarity","Lisa Sandström Painted Delicate Vacancy","Pia Winter Repairs Silent Study Better Field","Eugene Scott Lain Next To Joyfully Severing","Edward Cox Adapted To Hypnotic SciFi Relaxation","Samuel Ziegler Took Magical Blood","Joakim Åkesson Eats With Amazing Spirital Life","Денис Игнатьев Freezes Nervous Drone","Linus Engström Risked Being Chill Patience Wrapped In Silk","Johnny Lopez Entered Fatally Surrendering","Melissa Hall Pretends To Be First Spirital Of Eternal Star Shine","Sarah Allen Moved Along With Monotonously Cowering","Ulla Larsson Runs To Act Of Truth Spirit","Christopher Smith Recommends Risible Vibe","Hugo Lindström Informs Balanced Miracle Child","Надежда Ковалев Feed Ambitious Death","Sanna Saari Seemed To Be Serenity Silver Cosmos","Владимир Воронов Criticised Diesel Subwoofers With Obscure Cupcakes","Sandra Duda Provided A Whisper Of Awakening In Outer Space","Isabella Peters Denides Miserable Revolutionaries","Sharon Grant changed all Flower Of Exploring And Joy","Raymond Butler Became Demented Damage","Philipp Mayer Adore Serenity Silver Wrapped In Silk","John Lundberg Received Unconsciously Tweaking","Joshua White Grew Up With Flower Of Sci-Fi Waves","Alexander Schmidt Created Unconsciously Flirting","Bobby Allen Protects Soft Traveler Cleansing","Christopher Tucker Tried Diligently Kicking","Ida Niemelä Played With Soft Melancholy Cleansing","Jacqueline Cole Stands On Colorful Things From The Sewer","Camilla Månsson Pointed Out First Energy Waves","Morten Petersen Included All Cynical Craftsman","Андрей Абрамов Expands Breathing Soundscape Mindset","David Lee Fight For Poised Squirrels","Nathalie Axelsson Experiments With Choir Of Space Balance","Janet Richardson Forbid Subconscious Inspectors","Hans Ahmed Caught Amazing Energy In Your Dreams","Helena Johansson Heard Bionic Expectations","Lucas Meier Indicates Deep Ruby Mindset","Мария Анисимов Knows Spiffy Time","Matthew Mitchell Accepted Act Of Golden In The Dawning","Mattias Holm Demands Reflectively Snickering","Janet Anderson Shrank Inside Focus Waves","Sebastian Araya Saw Shrouded Junkies Forever","Heather Harrison Called For New Sci-Fi Driven By Birds","William Persson Served Festering Raisins Underwater","Carl Ferguson Was Astonished By Act Of Voyage To The Soul","Sofie Lunde Worked With Substantial Notturno","Madison Mason Calculates With Mindful Hypnobirthing Field","Ronald Daniels Generates Sentimental Dreams","Егор Соколов Believed In Divine SciFi In the Forest","Adriana Martínez Thought About Black And White Motions","Brandon Cruz Explores Natural Harmony Of Awareness","Ryan Ward Paid For Reserved Bones","Scott Snyder Broke Hypnotic Meditation Wrapped In Silk","Martha Hunter Watched Part-Time Sorrow","Gunilla Blomqvist Lit Up Asking For Voyage Therapy","Steven Fernandez Expected More From Reserved Endeavors","Oskar Oliszewski Stood Up Against Echoes Of Miracle Shadows","Anton Schwarz Spent Time With Spunky Advocates From Mars","Alicja Dudek Chose Internal Silver Cosmos","Thomas Smith Felt Nothing For Fantastic Epitaphs","Lena Müller Stopped Silent Silver In The River"],"id":830,"name":"Space Meditation Spa Music","img":{"number":"","underlined":false,"snakeCode":"","picture":{"hat":0,"eye":0,"human":0,"mouth":"_"},"grid":{"color":"","code":[[0,0,0,0],[0,0,0,0],[0,0,0,0],[0,0,0,0]]},"colors":[],"backgroundColor":""}}