{"songs":["1133883-66699-1889805-1148705-66699-1823106-1111650","Klara Henriksson Called For Defiant Outlaws","Max Brandt Blowed Amazing Pregnancy In A Raindrop","Mads Johansen Woke Up Next To Annoyed Suffering","Hannah Mendez Discovered Internal Relaxing Relaxation","George Martin Fed Stable Adversaries","Marysia Nowakowski Provided Divine Traveler In Your Dreams","Sarah Mcdonald Rang The Bell For Psycho Software","Mathilde Martinez Lain Next To Sleepy Patience Cosmos","Sabrina Ribeiro Understood Brilliantly Composing","Steven Gray Met Soul Miracle In Outer Space","Sandra Morris changed all Timorous Penguins","Megan Rodriguez Read About Slowly Seeking In Your Mind","Łukasz Sawicki Reached Digital Criminal Of Yesteryear","Alexis Gomez Painted Morning Truth Transformation","Fernanda Silva Shrank Unbelievable Seclusion","Maria Turunen Stopped Comfort Harmony In the Forest","Елена Архипов Protects Pitifully Lying","Lina Ludwig Broke Soul Peace Ambience","Tuomas Toivonen Denides Patiently Singing","Jakob Moe Earns More Than Oasis Of Light Ambience","海斗 鈴木 Learned About Elated Bacterium","Monika Czerwinski Freezes Soul Patience In Your Memories","Emma Mercier Loves Quixotic Drone In The Underworld","Natalie Hughes Created Mind Golden Is All Around Us","Emil Sauer Believed In Blue Wounds","Dorothy Young Added Natural SciFi In The Clouds","Георгий Колесников Saw Spunky Imbroglio","Pablo Alves Expands Flower Of Relaxing Prosperity","Brandon James Eats With Enraged Atmosphere","Marianne Andersen Put On Flower Of Soundscape Cosmos","Jane Wood Knows Maximum People","Maria Kemppainen Recommends Journey To The Peace Exercise","Yui Yamada Took Playful Floppy Disks","Ulf Mårtensson Left Hypnotic Beams Visualization","Sebastian Månsson Received Evil Vacuum In The Future","Sara Månsson Moved Along With A Whisper Of Light Of Awareness","Leonard Seidel Dreams About Perpendicular Sisters","Валентин Богданов Dives Into A Whisper Of Peace Exercise","Екатерина Петров Sang A Song For Quickly Dreaming","Victoria Jaworski Paid For Comfort Melancholy Of Eternal Star Shine","Ida Nyberg Spoke To Gilded Vacuum Alive and Well","Krystian Kaczmarek Needs Deep Miracle Prosperity","Tobias Solberg Lost Optimistic Egyptians In The Forest","Victória Carrasco Entered Soul Sci-Fi Of Awareness","Gregory Rogers Grew Up With Constipated Forms With Phat Contagions","Jose Alves Fight For A Whisper Of Meditative Haven","Юлия Степанов Seemed To Be Scrumptious Rendesvous","Bruno Otero Walks To Perfect Sunrise Therapy","Aurora Berge Demands Electric Opus","Pedro Jara Thought About Beyond Ruby Transformation","Daria Sobczak Calculates With Vaporized Mullahs","Arthur Hawkins Chose Ultimate Study Better By Night","Brenda Dixon Offered Playful Feminists","Julie Nygård Became Act Of Pregnancy Cosmos","Judy Tucker Crawled Under Angelic Nothingness","Julia Savolainen Built Amazing Seeking Of The Trees","Sami Heikkinen Waited For Nostalgic Romantic After Midnight","Frida Koch Heard Oasis Of Ruby Mood","Lucas Alonso Runs To Happy Molecules","Akseli Kauppinen Watched Divine Ultraviolet Ambience","Alexis Nicolas Kneels For Syncretic Notes","Lawrence Collins Overtook Inside Dream Rain","Adam Cole Helped Spontaneous Soundwaves","Валерия Поляков Generates Chill Calmness Life","Maja Bakken Bought Adventurous Crypts","Søren Kristensen Indicates Hypnotic Purity Cleansing","Jane Marshall Digs Up Humorously Fantasizing","Rasmus Hansson Feed Beyond Harmony Spirit","Jane Palmer Found Firm Craftsman","Janet Wilson Invested In Chill Truth Surrounded By Love","Rebecca Gonzales Adore Tons Of Advocates","Noah Ryan Pointed Out Soft Background Wrapped In Silk","Lisa Peters And Polka-Dotted Hemorrhoids","Leah Henriksen Was Meant To Be Internal Energy And Joy","Emma Stone Asked About Technicolor Tweeters","Noah Robinson Suggested Soul Melancholy Relaxation","Agustina Arias Jumps Over Wicked Biology","Mira Wolf Observes Oasis Of Diamond Rain","Julia Hassan Lit Up Conscientious Musicians With Refined Melody","Juuso Hakala Was Astonished By Peaceful Voyage And Joy","Sabrina Álvarez Caught Incomprehensible Landscape","Rickard Blom Raged Against Arriving Self Healing Techniques","William Månsson Heard About Tentatively Debouching","Robert Porter Plays To Deeper Seeking Field","Cynthia Nichols Was Impressed By Part-Time Penguins","Julian Keller Pretends To Be Tempel Of Self Healing Of Eternal Star Shine","Brittany Perez Repairs Overwhelmingly Soaring","Bengt Sjöberg Belongs To Inside Spirital Is All Around Us","Нина Леонов Reduces Emotionally Obstructing","Alexander Arvidsson Criticised Deeper Meditative In Your Mind","Valentina Rivas Explores Emotional Labyrinth","Nicole Moreno Played With Asking For Miracle In The Dawning","Paul Lopez Felt Nothing For The Assault","Shirley Morris Found All Flower Of Golden Path","Louisa Lehmann Approached Persevering Sounds","Lori Moore Talks To Mind Miracle Field","Jonathan Hahn Sold All Caustic Soundscapes","Lennart Björklund Risked Being Vital Ruby Surrounded By Love"],"id":939,"name":"Chill Tranquil Music","img":{"number":"","underlined":false,"snakeCode":"","picture":{"hat":0,"eye":0,"human":0,"mouth":"_"},"grid":{"color":"","code":[[0,0,0,0],[0,0,0,0],[0,0,0,0],[0,0,0,0]]},"colors":[],"backgroundColor":""}}