{
    "id": "1002",
    "img": {
        "number": "0053706146",
        "snakeCode": "'|.|'| |. '| |. ",
        "underlined": false,
        "idUnderlined": false,
        "picture": {
            "hat": "0",
            "eye": "1",
            "human": "1",
            "mouth": "_"
        },
        "grid": {
            "code": [
                [
                    "0",
                    "0",
                    "0",
                    "0"
                ],
                [
                    "0",
                    "0",
                    "0",
                    "0"
                ],
                [
                    "0",
                    "1",
                    "1",
                    "1"
                ],
                [
                    "0",
                    "0",
                    "0",
                    "0"
                ]
            ],
            "color": "#00ff01"
        },
        "colors": [
            "#988236",
            "#289e90",
            "#7c4390",
            "#196dcf",
            "#c27ba5",
            "#eb2f7b",
            "#ec757b"
        ],
        "backgroundColor": "#ea00ff"
    },
    "name": "Background Meditation Deep Music"
}