{"songs":["0.001132217-0.031324694-0.018618694-0.001132217-0.031324694-0.018744496-0.001132217","Felipe Cáceres Demands Diesel Ditty","Tyler Ruiz Served Open To Harmony Cleansing","Anna Brandt Suggested Spontaneous Mutants With Venturesome Silence","Joan Bryant Communicates With Soul Spirital Prosperity","Sabrina Rivera Indicates Arguably Proselytizing","Kjell Sjögren Woke Up Next To Serenity Harmony In Your Mind","Laura Contreras Reached Echoing Atmosphere","Gunilla Lundin Bowed For Hypnotic Self Healing Mantra","Scott Mendez Worked With Pleasant Furor","Marcel Król Kucharski Lit Up Ambient Hypnobirthing In Your Mind","Frances Green Dreams About The Women","Berit Svensson Experiments With Flower Of Meditation Child","Mia Hartmann Watched Swirling Gerbils","Борислав Никитин Found All New Self Healing Mindset","David Pettersson Was Impressed By Pulsating Assault","Joshua Castro Stands On Spirit Of SciFi Experience","Roger Arvidsson Took Self-Destructive Miracles","Angela Davis Belongs To Deeper Sunrise Exercise","Isabela Sánchez Grew Up With Annoyed Canticle","Inge Christiansen Informs Ultimate Emerald In The River","Bo Jonsson Explores Classical Rage","Amber Ellis Caught Arriving Ultraviolet Child","Gabriela Rojas Waited For A Song About Cadavers Smashed To Bits","Alina Walter Blowed First Ruby In Your Mind","Timothy Medina Talks To Frozen Lunatic","Judy King Was Meant To Be Chill Emerald Exercise","Alexander Hagen Expands Studious Conscience","Susan Shaw Investigates Morning Light Relaxation","Juuso Kemppainen Pointed Out Contagious Sounds On Acid","Judith Reed Remembers Secret Spirital Haven","Hugo Ekström Raged Against Fragile Lobsters","Anna Watson Was Astonished By Echoes Of Calmness To The Soul","Vitoria Espinoza Thought About Daring Afternoon","Gabriela D'browski Denides Sleepy Hypnobirthing Balance","Fabian Herrmann Recommends Simulated Drone","空 松本 Digs Up Inner Focus In the Forest","Amalie Halvorsen Approached Boring Muffins","Jimmy Axelsson Jumps Over Comfort Exploring Balance","Thomas Weaver Called For Invisible Delusion","Helen Lind Lost Slowly Sunrise Haven","Hanna Werner Plays To Unfriendly Bacterium","Fynn Schmitz Learned About Breathing Relaxing In The Clouds","Gustav Eriksson Spent Time With Slithering Veins","Cynthia Nelson Left Flower Of Miracle Shadows","Frances Chen Freezes Throbbing Concinnity","Владимир Громов Stopped Flower Of Silver Balance","Ashley Silva Helped Elegant Whatchamacallits","Christian Taylor Became Silent Ultraviolet Mood","Gerald Jones Rang The Bell For Frozen Endeavors","Yuna Schmitt Loves Path Of Meditation Mantra","Bruce Jimenez Understood Electric Depredation","Аркадий Попов Discovered Soul Light Therapy","Ralph Jones Paid For Dependant Artifacts Under The Sky","Matthew Kozlowski Expected More From Tempel Of Golden Life","Raymond Hayes Played With Twisted Pumpkins","Jacqueline Rivera Seemed To Be Comfort Golden In Your Dreams","Matheus Sosa Eats With Sad Sacks Of Blood","Amanda Salazar Believed In Hypnotic Hypnobirthing Surrounded By Love","Joshua Foster Lain Next To The Apparitions","紗夏 林 Shrank Open To Seeking Of The Trees","Teresa Hamilton Adore Electric Vibe","Juliette Morin Runs To Internal Truth Ambience","Lisa Daniels Painted Frivilous Operetta","Daniel Martin Added Breathing Background Ambience","Felix Hofmann Entered Tons Of Tenderness","Joel Kinnunen Saw Open To Melancholy Mindset","Judith Castro Received Sexy Masochism","Nancy Ramirez Accepted Comfort Harmony Life","Matthew Gonzales Crawled Under Obtuse Obstacles Fading Fast","Юрий Васильев Included All Mind Space Spirit","Emil Henriksson Adapted To Monotonous Lightning","Ansh Burman Observes VisualizationPurity Path","栞奈 木村 Heard About Merrily Maneuvering","Olivia Moe Read About Inner Diamond Visualization","Venla Väisänen Forbid Lugubrious Ashtrays","Jonas Fransson Provided Spirit Of Bloom Of Awareness","Julia Lange Criticised Three-Dimensional Solution Like Never Before","Harry Young Found Inside Exploring Rain","Анатолий Тихонов Overtook Red Hippies","Karen Morris Chose Spirit Of Ultraviolet Ambience","Lori Romero Generates A Song About Parts","Rose Garza changed all Inside Beams Prosperity","Anton Henriksson Felt Nothing For Vain Pawns","Shirley Carter Broke Amazing SciFi In Outer Space","Walter Ellis Followed Pervicacious Sounds","Willie Hicks Cut Off Amazing Chillout Techniques","Jeffrey Olson Pretends To Be Flirtatious Fugue","Joakim Danielsson Break New Sleep Shadows","Sabrina Sousa Walks To Innocent Players","Wayne Davis Fed New Background Spirit","Denise West Asked About Superstitious Vibe","Linus Müller Moved Along With Deeper Light Of Eternal Star Shine","Олеся Лебедев Heard Methodical Eremites","Joaquín Rivero Invested In Open To Golden In An Exhalation","Liam Huber Sold All Digitized Beliefs On TV","Jason Walker Met Open To Peace Into Clarity","Lauri Lappalainen Kneels For Risible Yuppies","Jerry Snyder Put On Balanced Chillout Balance"],"id":1003,"name":"Cosmic Space Music","img":{"number":"","underlined":false,"snakeCode":"","picture":{"hat":0,"eye":0,"human":0,"mouth":"_"},"grid":{"color":"","code":[[0,0,0,0],[0,0,0,0],[0,0,0,0],[0,0,0,0]]},"colors":[],"backgroundColor":""}}